phonemize/__init__.py
phonemize/phonemizer.py
phonemize/preprocess.py
phonemize/result.py
phonemize/train.py
phonemize/configs/__init__.py
phonemize/configs/autoreg_config.yaml
phonemize/configs/forward_config.yaml
phonemize/configs/forward_config_espeak_enrp.yaml
phonemize/configs/forward_config_espeak_enuk.yaml
phonemize/model/__init__.py
phonemize/model/model.py
phonemize/model/predictor.py
phonemize/model/utils.py
phonemize/preprocessing/__init__.py
phonemize/preprocessing/text.py
phonemize/preprocessing/utils.py
phonemize/training/__init__.py
phonemize/training/dataset.py
phonemize/training/decorators.py
phonemize/training/evaluation.py
phonemize/training/losses.py
phonemize/training/metrics.py
phonemize/training/trainer.py
phonemize/utils/__init__.py
phonemize/utils/io.py
phonemize/utils/logging.py
phonemize-0.2.4.dist-info/licenses/LICENSE
phonemize-0.2.4.dist-info/METADATA
phonemize-0.2.4.dist-info/WHEEL
phonemize-0.2.4.dist-info/top_level.txt
phonemize-0.2.4.dist-info/RECORD
