Metadata-Version: 2.4
Name: phonemize
Version: 0.2.4
Summary: Multilingual grapheme-to-phoneme (G2P) conversion using Transformer models.
Home-page: https://github.com/arcosoph/phonemize
Author: Arcosoph
Author-email: a5tkabid@gmail.com
License: MIT
Project-URL: Source, https://github.com/arcosoph/phonemize
Project-URL: Tracker, https://github.com/arcosoph/phonemize/issues
Classifier: Development Status :: 4 - Beta
Classifier: Intended Audience :: Developers
Classifier: Intended Audience :: Education
Classifier: Intended Audience :: Science/Research
Classifier: License :: OSI Approved :: MIT License
Classifier: Operating System :: POSIX :: Linux
Classifier: Operating System :: MacOS :: MacOS X
Classifier: Operating System :: Microsoft :: Windows
Classifier: Programming Language :: Python :: 3
Classifier: Programming Language :: Python :: 3.8
Classifier: Programming Language :: Python :: 3.9
Classifier: Programming Language :: Python :: 3.10
Classifier: Programming Language :: Python :: 3.11
Classifier: Programming Language :: Python :: 3.12
Classifier: Programming Language :: Python :: 3.13
Classifier: Topic :: Scientific/Engineering :: Artificial Intelligence
Classifier: Topic :: Software Development :: Libraries
Classifier: Topic :: Software Development :: Libraries :: Python Modules
Classifier: Topic :: Multimedia :: Sound/Audio :: Speech
Requires-Python: >=3.8
License-File: LICENSE
Requires-Dist: torch<2.9,>=2.8
Requires-Dist: numpy<3.0,>=2.0
Provides-Extra: dev
Requires-Dist: pyyaml; extra == "dev"
Requires-Dist: tqdm; extra == "dev"
Requires-Dist: tensorboard; extra == "dev"
Requires-Dist: flake8; extra == "dev"
Requires-Dist: mypy; extra == "dev"
Requires-Dist: pytest; extra == "dev"
Provides-Extra: train
Requires-Dist: tqdm; extra == "train"
Requires-Dist: tensorboard; extra == "train"
Requires-Dist: pyyaml; extra == "train"
Provides-Extra: all
Requires-Dist: pyyaml; extra == "all"
Requires-Dist: tqdm; extra == "all"
Requires-Dist: tensorboard; extra == "all"
Requires-Dist: flake8; extra == "all"
Requires-Dist: mypy; extra == "all"
Requires-Dist: pytest; extra == "all"
Dynamic: author
Dynamic: author-email
Dynamic: classifier
Dynamic: description
Dynamic: description-content-type
Dynamic: home-page
Dynamic: license
Dynamic: license-file
Dynamic: project-url
Dynamic: provides-extra
Dynamic: requires-dist
Dynamic: requires-python
Dynamic: summary
